cidc_api/config/__init__.py
cidc_api/config/db.py
cidc_api/config/logging.py
cidc_api/config/secrets.py
cidc_api/config/settings.py
cidc_api/csms/__init__.py
cidc_api/csms/auth.py
cidc_api/models/__init__.py
cidc_api/models/csms_api.py
cidc_api/models/migrations.py
cidc_api/models/models.py
cidc_api/models/schemas.py
cidc_api/models/files/__init__.py
cidc_api/models/files/details.py
cidc_api/models/files/facets.py
cidc_api/shared/__init__.py
cidc_api/shared/auth.py
cidc_api/shared/emails.py
cidc_api/shared/gcloud_client.py
cidc_api/shared/rest_utils.py
cidc_api_modules-0.27.46.dist-info/LICENSE
cidc_api_modules-0.27.46.dist-info/METADATA
cidc_api_modules-0.27.46.dist-info/WHEEL
cidc_api_modules-0.27.46.dist-info/top_level.txt
cidc_api_modules-0.27.46.dist-info/RECORD
