Metadata-Version: 2.1
Name: cidc-api-modules
Version: 0.27.46
Summary: SQLAlchemy data models and configuration tools used in the CIDC API
Home-page: https://github.com/CIMAC-CIDC/cidc_api-gae
License: MIT license
Requires-Python: >=3.6
License-File: LICENSE
Requires-Dist: werkzeug (==2.0.3)
Requires-Dist: flask (~=2.0.3)
Requires-Dist: flask-migrate (==2.5.2)
Requires-Dist: flask-sqlalchemy (~=2.4.0)
Requires-Dist: sqlalchemy (~=1.3.0)
Requires-Dist: marshmallow-sqlalchemy (==0.22.3)
Requires-Dist: google-cloud-storage (~=1.35.0)
Requires-Dist: google-cloud-pubsub (==0.42.1)
Requires-Dist: google-cloud-bigquery (==3.3.5)
Requires-Dist: google-api-python-client (==2.64.0)
Requires-Dist: pandas (==1.2.4)
Requires-Dist: python-dotenv (==0.10.3)
Requires-Dist: requests (==2.22.0)
Requires-Dist: jinja2 (~=3.0.3)
Requires-Dist: cidc-schemas (~=0.26.23)
